LICENSE
MANIFEST.in
README.md
requirements.txt
setup.py
tests.py
spotify/__init__.py
spotify/auth.py
spotify/client.py
spotify/endpoints.py
spotify_api.egg-info/PKG-INFO
spotify_api.egg-info/SOURCES.txt
spotify_api.egg-info/dependency_links.txt
spotify_api.egg-info/requires.txt
spotify_api.egg-info/top_level.txt