Metadata-Version: 1.0
Name: spotify-api
Version: 0.0.8
Summary: Python client for the Spotify web API
Home-page: https://github.com/steinitzu/spotify-api
Author: Steinthor Palsson
Author-email: steini90@gmail.com
License: MIT
Platform: UNKNOWN
